font_installer/__init__.py
font_installer/download.py
font_installer/posix.py
font_installer/windows.py
font_installer-0.1.2.dist-info/LICENSE
font_installer-0.1.2.dist-info/METADATA
font_installer-0.1.2.dist-info/WHEEL
font_installer-0.1.2.dist-info/entry_points.txt
font_installer-0.1.2.dist-info/top_level.txt
font_installer-0.1.2.dist-info/RECORD
