Metadata-Version: 2.1
Name: font-installer
Version: 0.1.2
Summary: UNKNOWN
Home-page: https://github.com/ineshbose/font-installer
Author: Inesh Bose
License: GPL
Keywords: font downloader google dafont
Platform: UNKNOWN
Classifier: Programming Language :: Python :: 3
Classifier: License :: OSI Approved :: GNU General Public License (GPL)
Requires-Dist: certifi (==2020.4.5.1)
Requires-Dist: chardet (==3.0.4)
Requires-Dist: idna (==2.9)
Requires-Dist: requests (==2.23.0)
Requires-Dist: urllib3 (==1.25.9)
